LICENSE
MANIFEST.in
README.rst
btlroute.py
setup.py
btlroute.egg-info/PKG-INFO
btlroute.egg-info/SOURCES.txt
btlroute.egg-info/dependency_links.txt
btlroute.egg-info/top_level.txt
test/__init__.py
test/test_router.py