Metadata-Version: 1.1
Name: btlroute
Version: 0.12.1
Summary: URL Route parser HEAVILY based on Bottle Web server
Home-page: UNKNOWN
Author: Carlos Martín
Author-email: ['marc@gsites.de', 'inean.es@gmail.com']
License: MIT
Platform: any
Classifier: Development Status :: 4 - Beta
Classifier: Intended Audience :: Developers
Classifier: License :: OSI Approved :: MIT License
Classifier: Topic :: Software Development :: Libraries
Classifier: Programming Language :: Python :: 2.5
Classifier: Programming Language :: Python :: 2.6
Classifier: Programming Language :: Python :: 2.7
Classifier: Programming Language :: Python :: 3
